motto/__init__.py
motto/cli.py
motto/core/__init__.py
motto/core/base.py
motto/core/config.py
motto/core/default.cfg
motto/core/loaders.py
motto/core/readers.py
motto/core/transforms.py
motto/core/writers.py
motto/skills/__init__.py
motto/skills/reporting.py
motto/skills/sentence_length.py
motto-0.1.1.dist-info/entry_points.txt
motto-0.1.1.dist-info/LICENSE
motto-0.1.1.dist-info/WHEEL
motto-0.1.1.dist-info/METADATA
motto-0.1.1.dist-info/RECORD
